{
  "id": "cofagrigus",
  "dexnum": 563,
  "name": "Cofagrigus",
  "nameFr": "Tutankafer",
  "description": "Il prend l'apparence d'un beau cercueil. Les pilleurs de tombes imprudents finissent enfermés à l'intérieur.",
  "primaryType": "ghost",
  "secondaryType": "",
  "primaryTypeFr": "Spectre",
  "secondaryTypeFr": "",
  "height": 17,
  "weight": 765,
  "maleRatio": 0.5,
  "baseScale": 0.8,
  "hitbox": {
    "width": 1.5,
    "height": 3.3,
    "fixed": false
  },
  "labels": [
    "gen5"
  ],
  "abilities": [
    {
      "id": "mummy",
      "name": "Momie",
      "hidden": false
    },
    {
      "id": "mummy",
      "name": "Momie",
      "hidden": true
    }
  ],
  "eggGroups": [
    "mineral",
    "amorphous"
  ],
  "eggCycles": 25,
  "baseStats": {
    "hp": 58,
    "attack": 50,
    "defence": 145,
    "special_attack": 95,
    "special_defence": 105,
    "speed": 30
  },
  "evYield": {
    "hp": 0,
    "attack": 0,
    "defence": 2,
    "special_attack": 0,
    "special_defence": 0,
    "speed": 0
  },
  "baseExperienceYield": 169,
  "experienceGroup": "medium_fast",
  "catchRate": 90,
  "baseFriendship": 50,
  "drops": {
    "amount": 1,
    "entries": [
      {
        "item": "cobblemon:spell_tag",
        "percentage": 5.0,
        "quantityRange": null,
        "source": "species",
        "itemName": "Rune Sort"
      }
    ]
  },
  "moves": [
    {
      "id": "astonish",
      "name": "Étonnement",
      "category": "1"
    },
    {
      "id": "protect",
      "name": "Abri",
      "category": "1"
    },
    {
      "id": "haze",
      "name": "Buée Noire",
      "category": "1"
    },
    {
      "id": "nightshade",
      "name": "Ombre Nocturne",
      "category": "1"
    },
    {
      "id": "scaryface",
      "name": "Grimace",
      "category": "1"
    },
    {
      "id": "shadowclaw",
      "name": "Griffe Ombre",
      "category": "1"
    },
    {
      "id": "disable",
      "name": "Entrave",
      "category": "12"
    },
    {
      "id": "willowisp",
      "name": "Feu Follet",
      "category": "16"
    },
    {
      "id": "craftyshield",
      "name": "Vigilance",
      "category": "20"
    },
    {
      "id": "hex",
      "name": "Châtiment",
      "category": "24"
    },
    {
      "id": "meanlook",
      "name": "Regard Noir",
      "category": "28"
    },
    {
      "id": "grudge",
      "name": "Rancune",
      "category": "32"
    },
    {
      "id": "curse",
      "name": "Malédiction",
      "category": "38"
    },
    {
      "id": "shadowball",
      "name": "Ball'Ombre",
      "category": "44"
    },
    {
      "id": "darkpulse",
      "name": "Vibrobscur",
      "category": "50"
    },
    {
      "id": "powersplit",
      "name": "Partage Force",
      "category": "56"
    },
    {
      "id": "guardsplit",
      "name": "Partage Garde",
      "category": "56"
    },
    {
      "id": "destinybond",
      "name": "Lien du Destin",
      "category": "62"
    },
    {
      "id": "healblock",
      "name": "Anti-Soin",
      "category": "egg"
    },
    {
      "id": "memento",
      "name": "Souvenir",
      "category": "egg"
    },
    {
      "id": "nightmare",
      "name": "Cauchemar",
      "category": "egg"
    },
    {
      "id": "afteryou",
      "name": "Après Vous",
      "category": "tm"
    },
    {
      "id": "allyswitch",
      "name": "Interversion",
      "category": "tm"
    },
    {
      "id": "block",
      "name": "Barrage",
      "category": "tm"
    },
    {
      "id": "bodypress",
      "name": "Big Splash",
      "category": "tm"
    },
    {
      "id": "calmmind",
      "name": "Plénitude",
      "category": "tm"
    },
    {
      "id": "curse",
      "name": "Malédiction",
      "category": "tm"
    },
    {
      "id": "darkpulse",
      "name": "Vibrobscur",
      "category": "tm"
    },
    {
      "id": "dreameater",
      "name": "Dévorêve",
      "category": "tm"
    },
    {
      "id": "embargo",
      "name": "Embargo",
      "category": "tm"
    },
    {
      "id": "endure",
      "name": "Ténacité",
      "category": "tm"
    },
    {
      "id": "energyball",
      "name": "Éco-Sphère",
      "category": "tm"
    },
    {
      "id": "facade",
      "name": "Façade",
      "category": "tm"
    },
    {
      "id": "faketears",
      "name": "Croco Larme",
      "category": "tm"
    },
    {
      "id": "flash",
      "name": "Flash",
      "category": "tm"
    },
    {
      "id": "gigaimpact",
      "name": "Giga Impact",
      "category": "tm"
    },
    {
      "id": "grassknot",
      "name": "Nœud Herbe",
      "category": "tm"
    },
    {
      "id": "guardswap",
      "name": "Permugarde",
      "category": "tm"
    },
    {
      "id": "haze",
      "name": "Buée Noire",
      "category": "tm"
    },
    {
      "id": "hex",
      "name": "Châtiment",
      "category": "tm"
    },
    {
      "id": "hyperbeam",
      "name": "Ultralaser",
      "category": "tm"
    },
    {
      "id": "imprison",
      "name": "Possessif",
      "category": "tm"
    },
    {
      "id": "infestation",
      "name": "Harcèlement",
      "category": "tm"
    },
    {
      "id": "irondefense",
      "name": "Mur de Fer",
      "category": "tm"
    },
    {
      "id": "knockoff",
      "name": "Sabotage",
      "category": "tm"
    },
    {
      "id": "magiccoat",
      "name": "Reflet Magik",
      "category": "tm"
    },
    {
      "id": "nastyplot",
      "name": "Machination",
      "category": "tm"
    },
    {
      "id": "nightshade",
      "name": "Ombre Nocturne",
      "category": "tm"
    },
    {
      "id": "ominouswind",
      "name": "Vent Mauvais",
      "category": "tm"
    },
    {
      "id": "painsplit",
      "name": "Balance",
      "category": "tm"
    },
    {
      "id": "payback",
      "name": "Représailles",
      "category": "tm"
    },
    {
      "id": "phantomforce",
      "name": "Hantise",
      "category": "tm"
    },
    {
      "id": "poltergeist",
      "name": "Esprit Frappeur",
      "category": "tm"
    },
    {
      "id": "powerswap",
      "name": "Permuforce",
      "category": "tm"
    },
    {
      "id": "protect",
      "name": "Abri",
      "category": "tm"
    },
    {
      "id": "psychic",
      "name": "Psyko",
      "category": "tm"
    },
    {
      "id": "psychup",
      "name": "Boost",
      "category": "tm"
    },
    {
      "id": "raindance",
      "name": "Danse Pluie",
      "category": "tm"
    },
    {
      "id": "rest",
      "name": "Repos",
      "category": "tm"
    },
    {
      "id": "revenge",
      "name": "Vendetta",
      "category": "tm"
    },
    {
      "id": "roleplay",
      "name": "Imitation",
      "category": "tm"
    },
    {
      "id": "safeguard",
      "name": "Rune Protect",
      "category": "tm"
    },
    {
      "id": "scaryface",
      "name": "Grimace",
      "category": "tm"
    },
    {
      "id": "shadowball",
      "name": "Ball'Ombre",
      "category": "tm"
    },
    {
      "id": "shadowclaw",
      "name": "Griffe Ombre",
      "category": "tm"
    },
    {
      "id": "shockwave",
      "name": "Onde de Choc",
      "category": "tm"
    },
    {
      "id": "skillswap",
      "name": "Échange",
      "category": "tm"
    },
    {
      "id": "sleeptalk",
      "name": "Blabla Dodo",
      "category": "tm"
    },
    {
      "id": "snatch",
      "name": "Saisie",
      "category": "tm"
    },
    {
      "id": "spite",
      "name": "Dépit",
      "category": "tm"
    },
    {
      "id": "substitute",
      "name": "Clonage",
      "category": "tm"
    },
    {
      "id": "telekinesis",
      "name": "Lévikinésie",
      "category": "tm"
    },
    {
      "id": "terablast",
      "name": "Téra Explosion",
      "category": "tm"
    },
    {
      "id": "thief",
      "name": "Larcin",
      "category": "tm"
    },
    {
      "id": "toxicspikes",
      "name": "Pics Toxik",
      "category": "tm"
    },
    {
      "id": "trick",
      "name": "Tour de Magie",
      "category": "tm"
    },
    {
      "id": "trickroom",
      "name": "Distorsion",
      "category": "tm"
    },
    {
      "id": "willowisp",
      "name": "Feu Follet",
      "category": "tm"
    },
    {
      "id": "wonderroom",
      "name": "Zone Étrange",
      "category": "tm"
    },
    {
      "id": "zenheadbutt",
      "name": "Psykoud'Boul",
      "category": "tm"
    },
    {
      "id": "afteryou",
      "name": "Après Vous",
      "category": "tutor"
    },
    {
      "id": "allyswitch",
      "name": "Interversion",
      "category": "tutor"
    },
    {
      "id": "block",
      "name": "Barrage",
      "category": "tutor"
    },
    {
      "id": "calmmind",
      "name": "Plénitude",
      "category": "tutor"
    },
    {
      "id": "darkpulse",
      "name": "Vibrobscur",
      "category": "tutor"
    },
    {
      "id": "energyball",
      "name": "Éco-Sphère",
      "category": "tutor"
    },
    {
      "id": "gigaimpact",
      "name": "Giga Impact",
      "category": "tutor"
    },
    {
      "id": "hyperbeam",
      "name": "Ultralaser",
      "category": "tutor"
    },
    {
      "id": "irondefense",
      "name": "Mur de Fer",
      "category": "tutor"
    },
    {
      "id": "knockoff",
      "name": "Sabotage",
      "category": "tutor"
    },
    {
      "id": "magiccoat",
      "name": "Reflet Magik",
      "category": "tutor"
    },
    {
      "id": "ominouswind",
      "name": "Vent Mauvais",
      "category": "tutor"
    },
    {
      "id": "painsplit",
      "name": "Balance",
      "category": "tutor"
    },
    {
      "id": "poltergeist",
      "name": "Esprit Frappeur",
      "category": "tutor"
    },
    {
      "id": "psychic",
      "name": "Psyko",
      "category": "tutor"
    },
    {
      "id": "rest",
      "name": "Repos",
      "category": "tutor"
    },
    {
      "id": "roleplay",
      "name": "Imitation",
      "category": "tutor"
    },
    {
      "id": "shadowball",
      "name": "Ball'Ombre",
      "category": "tutor"
    },
    {
      "id": "shadowclaw",
      "name": "Griffe Ombre",
      "category": "tutor"
    },
    {
      "id": "shockwave",
      "name": "Onde de Choc",
      "category": "tutor"
    },
    {
      "id": "skillswap",
      "name": "Échange",
      "category": "tutor"
    },
    {
      "id": "sleeptalk",
      "name": "Blabla Dodo",
      "category": "tutor"
    },
    {
      "id": "snatch",
      "name": "Saisie",
      "category": "tutor"
    },
    {
      "id": "spite",
      "name": "Dépit",
      "category": "tutor"
    },
    {
      "id": "telekinesis",
      "name": "Lévikinésie",
      "category": "tutor"
    },
    {
      "id": "trick",
      "name": "Tour de Magie",
      "category": "tutor"
    },
    {
      "id": "wonderroom",
      "name": "Zone Étrange",
      "category": "tutor"
    },
    {
      "id": "zenheadbutt",
      "name": "Psykoud'Boul",
      "category": "tutor"
    },
    {
      "id": "attract",
      "name": "Attraction",
      "category": "legacy"
    },
    {
      "id": "confide",
      "name": "Confidence",
      "category": "legacy"
    },
    {
      "id": "doubleteam",
      "name": "Reflet",
      "category": "legacy"
    },
    {
      "id": "frustration",
      "name": "Frustration",
      "category": "legacy"
    },
    {
      "id": "hiddenpower",
      "name": "Puissance Cachée",
      "category": "legacy"
    },
    {
      "id": "return",
      "name": "Retour",
      "category": "legacy"
    },
    {
      "id": "round",
      "name": "Chant Canon",
      "category": "legacy"
    },
    {
      "id": "secretpower",
      "name": "Force Cachée",
      "category": "legacy"
    },
    {
      "id": "snore",
      "name": "Ronflement",
      "category": "legacy"
    },
    {
      "id": "swagger",
      "name": "Vantardise",
      "category": "legacy"
    },
    {
      "id": "toxic",
      "name": "Toxik",
      "category": "legacy"
    }
  ],
  "forms": [],
  "evolutions": [],
  "preEvolution": "yamask",
  "spawns": [
    [
      {
        "presets": [
          "natural"
        ],
        "rarity": "uncommon",
        "weight": 0.32,
        "levels": "34-48",
        "biomeTags": {
          "include": [
            "#cobblemon:is_desert"
          ],
          "exclude": [
            "#cobblemon:is_deep_dark"
          ]
        },
        "source": "Abes-Hutts-Cobblemon-1.21.1.1.7.3-1.0.2.jar!/data/cobblemon/spawn_pool_world/0563_cofagrigus.json",
        "spawnId": "cofagrigus-1",
        "sky": {
          "minSkyLight": 0,
          "maxSkyLight": 7
        },
        "spawnType": "grounded",
        "pokemon": "cofagrigus",
        "type": "pokemon"
      }
    ],
    [
      {
        "presets": [
          "natural",
          "desert_pyramid"
        ],
        "rarity": "common",
        "weight": 10.0,
        "levels": "34-48",
        "biomeTags": {
          "include": [
            "#cobblemon:is_overworld"
          ]
        },
        "source": "Abes-Hutts-Cobblemon-1.21.1.1.7.3-1.0.2.jar!/data/cobblemon/spawn_pool_world/0563_cofagrigus.json",
        "spawnId": "cofagrigus-2",
        "sky": {
          "canSeeSky": false
        },
        "yLevel": {
          "minY": 48
        },
        "spawnType": "grounded",
        "pokemon": "cofagrigus",
        "type": "pokemon"
      }
    ]
  ],
  "implemented": true,
  "images": {
    "normal": [
      "out/sprites/cobblemon/cofagrigus.png"
    ],
    "shiny": [
      "out/sprites/cobblemon/cofagrigus_shiny.png"
    ]
  },
  "speciesSources": [
    "Abes-Hutts-Cobblemon-1.21.1.1.7.3-1.0.2.jar!/data/cobblemon/species/generation5/cofagrigus.json"
  ]
}