{
  "id": "crocalor",
  "dexnum": 910,
  "name": "Crocalor",
  "nameFr": "Crocogril",
  "description": "La boule de feu en forme d'œuf qui surmonte sa tête résulte de la fusion entre son énergie de type Feu et son trop-plein de vitalité.",
  "primaryType": "fire",
  "secondaryType": "",
  "primaryTypeFr": "Feu",
  "secondaryTypeFr": "",
  "height": 10,
  "weight": 307,
  "maleRatio": 0.875,
  "baseScale": 0.7,
  "hitbox": {
    "width": 1,
    "height": 1.4,
    "fixed": false
  },
  "labels": [
    "gen9"
  ],
  "abilities": [
    {
      "id": "blaze",
      "name": "Brasier",
      "hidden": false
    },
    {
      "id": "unaware",
      "name": "Inconscient",
      "hidden": true
    }
  ],
  "eggGroups": [
    "field"
  ],
  "eggCycles": 20,
  "baseStats": {
    "hp": 81,
    "attack": 55,
    "defence": 78,
    "special_attack": 90,
    "special_defence": 58,
    "speed": 49
  },
  "evYield": {
    "hp": 0,
    "attack": 0,
    "defence": 0,
    "special_attack": 2,
    "special_defence": 0,
    "speed": 0
  },
  "baseExperienceYield": 144,
  "experienceGroup": "medium_slow",
  "catchRate": 45,
  "baseFriendship": 50,
  "drops": {
    "amount": 1,
    "entries": [
      {
        "item": "cobblemon:charcoal_stick",
        "percentage": 10.0,
        "quantityRange": null,
        "source": "species",
        "itemName": "Bâton de charbon"
      }
    ]
  },
  "moves": [
    {
      "id": "tackle",
      "name": "Charge",
      "category": "1"
    },
    {
      "id": "leer",
      "name": "Groz'Yeux",
      "category": "1"
    },
    {
      "id": "ember",
      "name": "Flammèche",
      "category": "1"
    },
    {
      "id": "lick",
      "name": "Léchouille",
      "category": "7"
    },
    {
      "id": "round",
      "name": "Chant Canon",
      "category": "10"
    },
    {
      "id": "bite",
      "name": "Morsure",
      "category": "12"
    },
    {
      "id": "yawn",
      "name": "Bâillement",
      "category": "15"
    },
    {
      "id": "incinerate",
      "name": "Calcination",
      "category": "17"
    },
    {
      "id": "snarl",
      "name": "Aboiement",
      "category": "24"
    },
    {
      "id": "roar",
      "name": "Hurlement",
      "category": "28"
    },
    {
      "id": "flamethrower",
      "name": "Lance-Flammes",
      "category": "32"
    },
    {
      "id": "hypervoice",
      "name": "Mégaphone",
      "category": "38"
    },
    {
      "id": "willowisp",
      "name": "Feu Follet",
      "category": "42"
    },
    {
      "id": "fireblast",
      "name": "Déflagration",
      "category": "47"
    },
    {
      "id": "belch",
      "name": "Éructation",
      "category": "egg"
    },
    {
      "id": "curse",
      "name": "Malédiction",
      "category": "egg"
    },
    {
      "id": "encore",
      "name": "Encore",
      "category": "egg"
    },
    {
      "id": "slackoff",
      "name": "Paresse",
      "category": "egg"
    },
    {
      "id": "bodyslam",
      "name": "Plaquage",
      "category": "tm"
    },
    {
      "id": "crunch",
      "name": "Mâchouille",
      "category": "tm"
    },
    {
      "id": "curse",
      "name": "Malédiction",
      "category": "tm"
    },
    {
      "id": "dig",
      "name": "Tunnel",
      "category": "tm"
    },
    {
      "id": "disarmingvoice",
      "name": "Voix Enjôleuse",
      "category": "tm"
    },
    {
      "id": "encore",
      "name": "Encore",
      "category": "tm"
    },
    {
      "id": "endure",
      "name": "Ténacité",
      "category": "tm"
    },
    {
      "id": "facade",
      "name": "Façade",
      "category": "tm"
    },
    {
      "id": "fireblast",
      "name": "Déflagration",
      "category": "tm"
    },
    {
      "id": "firefang",
      "name": "Crocs Feu",
      "category": "tm"
    },
    {
      "id": "firepledge",
      "name": "Aire de Feu",
      "category": "tm"
    },
    {
      "id": "firespin",
      "name": "Danse Flammes",
      "category": "tm"
    },
    {
      "id": "flamecharge",
      "name": "Nitrocharge",
      "category": "tm"
    },
    {
      "id": "flamethrower",
      "name": "Lance-Flammes",
      "category": "tm"
    },
    {
      "id": "flareblitz",
      "name": "Boutefeu",
      "category": "tm"
    },
    {
      "id": "heatwave",
      "name": "Canicule",
      "category": "tm"
    },
    {
      "id": "helpinghand",
      "name": "Coup d'Main",
      "category": "tm"
    },
    {
      "id": "hypervoice",
      "name": "Mégaphone",
      "category": "tm"
    },
    {
      "id": "incinerate",
      "name": "Calcination",
      "category": "tm"
    },
    {
      "id": "mudslap",
      "name": "Coud'Boue",
      "category": "tm"
    },
    {
      "id": "outrage",
      "name": "Colère",
      "category": "tm"
    },
    {
      "id": "overheat",
      "name": "Surchauffe",
      "category": "tm"
    },
    {
      "id": "protect",
      "name": "Abri",
      "category": "tm"
    },
    {
      "id": "rest",
      "name": "Repos",
      "category": "tm"
    },
    {
      "id": "roar",
      "name": "Hurlement",
      "category": "tm"
    },
    {
      "id": "round",
      "name": "Chant Canon",
      "category": "tm"
    },
    {
      "id": "seedbomb",
      "name": "Canon Graine",
      "category": "tm"
    },
    {
      "id": "sleeptalk",
      "name": "Blabla Dodo",
      "category": "tm"
    },
    {
      "id": "snarl",
      "name": "Aboiement",
      "category": "tm"
    },
    {
      "id": "stompingtantrum",
      "name": "Trépignement",
      "category": "tm"
    },
    {
      "id": "substitute",
      "name": "Clonage",
      "category": "tm"
    },
    {
      "id": "sunnyday",
      "name": "Zénith",
      "category": "tm"
    },
    {
      "id": "takedown",
      "name": "Bélier",
      "category": "tm"
    },
    {
      "id": "temperflare",
      "name": "Indignition",
      "category": "tm"
    },
    {
      "id": "terablast",
      "name": "Téra Explosion",
      "category": "tm"
    },
    {
      "id": "thunderfang",
      "name": "Crocs Éclair",
      "category": "tm"
    },
    {
      "id": "willowisp",
      "name": "Feu Follet",
      "category": "tm"
    },
    {
      "id": "zenheadbutt",
      "name": "Psykoud'Boul",
      "category": "tm"
    },
    {
      "id": "firefang",
      "name": "Crocs Feu",
      "category": "tutor"
    },
    {
      "id": "firepledge",
      "name": "Aire de Feu",
      "category": "tutor"
    },
    {
      "id": "flamethrower",
      "name": "Lance-Flammes",
      "category": "tutor"
    },
    {
      "id": "heatwave",
      "name": "Canicule",
      "category": "tutor"
    },
    {
      "id": "helpinghand",
      "name": "Coup d'Main",
      "category": "tutor"
    },
    {
      "id": "hypervoice",
      "name": "Mégaphone",
      "category": "tutor"
    },
    {
      "id": "mudslap",
      "name": "Coud'Boue",
      "category": "tutor"
    },
    {
      "id": "outrage",
      "name": "Colère",
      "category": "tutor"
    },
    {
      "id": "rest",
      "name": "Repos",
      "category": "tutor"
    },
    {
      "id": "seedbomb",
      "name": "Canon Graine",
      "category": "tutor"
    },
    {
      "id": "sleeptalk",
      "name": "Blabla Dodo",
      "category": "tutor"
    },
    {
      "id": "snarl",
      "name": "Aboiement",
      "category": "tutor"
    },
    {
      "id": "stompingtantrum",
      "name": "Trépignement",
      "category": "tutor"
    },
    {
      "id": "thunderfang",
      "name": "Crocs Éclair",
      "category": "tutor"
    },
    {
      "id": "zenheadbutt",
      "name": "Psykoud'Boul",
      "category": "tutor"
    }
  ],
  "forms": [],
  "evolutions": [
    {
      "id": "crocalor_skeledirge",
      "variant": "level_up",
      "result": "skeledirge",
      "consumeHeldItem": false,
      "learnableMoves": [
        "torchsong"
      ],
      "requirements": [
        {
          "variant": "level",
          "minLevel": 36
        }
      ]
    }
  ],
  "preEvolution": "fuecoco",
  "spawns": [
    [
      {
        "presets": [
          "natural"
        ],
        "rarity": "ultra-rare",
        "weight": 3.6,
        "levels": "16-41",
        "biomeTags": {
          "include": [
            "#cobblemon:is_badlands"
          ]
        },
        "source": "Abes-Hutts-Cobblemon-1.21.1.1.7.3-1.0.2.jar!/data/cobblemon/spawn_pool_world/0910_crocalor.json",
        "spawnId": "crocalor-1",
        "sky": {
          "minSkyLight": 8,
          "maxSkyLight": 15
        },
        "spawnType": "grounded",
        "pokemon": "crocalor",
        "type": "pokemon"
      }
    ],
    [
      {
        "presets": [
          "natural"
        ],
        "rarity": "ultra-rare",
        "weight": 3.6,
        "levels": "16-41",
        "biomeTags": {
          "include": [
            "#cobblemon:nether/is_wasteland"
          ]
        },
        "source": "Abes-Hutts-Cobblemon-1.21.1.1.7.3-1.0.2.jar!/data/cobblemon/spawn_pool_world/0910_crocalor.json",
        "spawnId": "crocalor-2",
        "spawnType": "grounded",
        "pokemon": "crocalor",
        "type": "pokemon"
      }
    ]
  ],
  "implemented": true,
  "images": {
    "normal": [
      "out/sprites/cobblemon/crocalor.png"
    ],
    "shiny": [
      "out/sprites/cobblemon/crocalor_shiny.png"
    ]
  },
  "speciesSources": [
    "Abes-Hutts-Cobblemon-1.21.1.1.7.3-1.0.2.jar!/data/cobblemon/species/generation9/crocalor.json"
  ]
}