{
  "id": "sunflora",
  "dexnum": 192,
  "name": "Sunflora",
  "nameFr": "Héliatronc",
  "description": "Héliatronc convertit l'énergie solaire en nutriments. Il remue activement pendant la journée, quand il fait chaud. Il redevient immobile dès que le soleil se couche.",
  "primaryType": "grass",
  "secondaryType": "",
  "primaryTypeFr": "Plante",
  "secondaryTypeFr": "",
  "height": 8,
  "weight": 85,
  "maleRatio": 0.5,
  "baseScale": 0.8,
  "hitbox": {
    "width": 0.75,
    "height": 1.38,
    "fixed": false
  },
  "labels": [
    "gen2"
  ],
  "abilities": [
    {
      "id": "chlorophyll",
      "name": "Chlorophylle",
      "hidden": false
    },
    {
      "id": "solarpower",
      "name": "Force Soleil",
      "hidden": false
    },
    {
      "id": "earlybird",
      "name": "Matinal",
      "hidden": true
    }
  ],
  "eggGroups": [
    "grass"
  ],
  "eggCycles": 20,
  "baseStats": {
    "hp": 75,
    "attack": 75,
    "defence": 55,
    "special_attack": 105,
    "special_defence": 85,
    "speed": 30
  },
  "evYield": {
    "hp": 0,
    "attack": 0,
    "defence": 0,
    "special_attack": 2,
    "special_defence": 0,
    "speed": 0
  },
  "baseExperienceYield": 149,
  "experienceGroup": "medium_slow",
  "catchRate": 120,
  "baseFriendship": 50,
  "drops": {
    "amount": 2,
    "entries": [
      {
        "item": "minecraft:sunflower",
        "percentage": null,
        "quantityRange": null,
        "source": "species",
        "itemName": "minecraft:sunflower"
      },
      {
        "item": "cobblemon:coba_berry",
        "percentage": 5.0,
        "quantityRange": null,
        "source": "species",
        "itemName": "Baie Cobaba"
      }
    ]
  },
  "moves": [
    {
      "id": "pound",
      "name": "Écras'Face",
      "category": "1"
    },
    {
      "id": "growth",
      "name": "Croissance",
      "category": "1"
    },
    {
      "id": "grasswhistle",
      "name": "Siffl'Herbe",
      "category": "1"
    },
    {
      "id": "flowershield",
      "name": "Garde Florale",
      "category": "1"
    },
    {
      "id": "naturalgift",
      "name": "Don Naturel",
      "category": "1"
    },
    {
      "id": "tackle",
      "name": "Charge",
      "category": "1"
    },
    {
      "id": "ingrain",
      "name": "Racines",
      "category": "4"
    },
    {
      "id": "absorb",
      "name": "Vole-Vie",
      "category": "7"
    },
    {
      "id": "megadrain",
      "name": "Méga-Sangsue",
      "category": "10"
    },
    {
      "id": "leechseed",
      "name": "Vampigraine",
      "category": "13"
    },
    {
      "id": "razorleaf",
      "name": "Tranch'Herbe",
      "category": "16"
    },
    {
      "id": "worryseed",
      "name": "Soucigraine",
      "category": "19"
    },
    {
      "id": "gigadrain",
      "name": "Giga-Sangsue",
      "category": "22"
    },
    {
      "id": "bulletseed",
      "name": "Balle Graine",
      "category": "25"
    },
    {
      "id": "petaldance",
      "name": "Danse Fleurs",
      "category": "28"
    },
    {
      "id": "solarbeam",
      "name": "Lance-Soleil",
      "category": "31"
    },
    {
      "id": "doubleedge",
      "name": "Damoclès",
      "category": "34"
    },
    {
      "id": "sunnyday",
      "name": "Zénith",
      "category": "39"
    },
    {
      "id": "leafstorm",
      "name": "Tempête Verte",
      "category": "43"
    },
    {
      "id": "petalblizzard",
      "name": "Tempête Florale",
      "category": "50"
    },
    {
      "id": "bide",
      "name": "Patience",
      "category": "egg"
    },
    {
      "id": "curse",
      "name": "Malédiction",
      "category": "egg"
    },
    {
      "id": "encore",
      "name": "Encore",
      "category": "egg"
    },
    {
      "id": "grasswhistle",
      "name": "Siffl'Herbe",
      "category": "egg"
    },
    {
      "id": "grassyterrain",
      "name": "Champ Herbu",
      "category": "egg"
    },
    {
      "id": "ingrain",
      "name": "Racines",
      "category": "egg"
    },
    {
      "id": "leechseed",
      "name": "Vampigraine",
      "category": "egg"
    },
    {
      "id": "morningsun",
      "name": "Aurore",
      "category": "egg"
    },
    {
      "id": "naturalgift",
      "name": "Don Naturel",
      "category": "egg"
    },
    {
      "id": "sweetscent",
      "name": "Doux Parfum",
      "category": "egg"
    },
    {
      "id": "afteryou",
      "name": "Après Vous",
      "category": "tm"
    },
    {
      "id": "bulletseed",
      "name": "Balle Graine",
      "category": "tm"
    },
    {
      "id": "curse",
      "name": "Malédiction",
      "category": "tm"
    },
    {
      "id": "cut",
      "name": "Coupe",
      "category": "tm"
    },
    {
      "id": "dazzlinggleam",
      "name": "Éclat Magique",
      "category": "tm"
    },
    {
      "id": "doubleedge",
      "name": "Damoclès",
      "category": "tm"
    },
    {
      "id": "earthpower",
      "name": "Telluriforce",
      "category": "tm"
    },
    {
      "id": "encore",
      "name": "Encore",
      "category": "tm"
    },
    {
      "id": "endeavor",
      "name": "Effort",
      "category": "tm"
    },
    {
      "id": "endure",
      "name": "Ténacité",
      "category": "tm"
    },
    {
      "id": "energyball",
      "name": "Éco-Sphère",
      "category": "tm"
    },
    {
      "id": "facade",
      "name": "Façade",
      "category": "tm"
    },
    {
      "id": "flash",
      "name": "Flash",
      "category": "tm"
    },
    {
      "id": "gigadrain",
      "name": "Giga-Sangsue",
      "category": "tm"
    },
    {
      "id": "gigaimpact",
      "name": "Giga Impact",
      "category": "tm"
    },
    {
      "id": "grassknot",
      "name": "Nœud Herbe",
      "category": "tm"
    },
    {
      "id": "grassyglide",
      "name": "Gliss'Herbe",
      "category": "tm"
    },
    {
      "id": "grassyterrain",
      "name": "Champ Herbu",
      "category": "tm"
    },
    {
      "id": "helpinghand",
      "name": "Coup d'Main",
      "category": "tm"
    },
    {
      "id": "hyperbeam",
      "name": "Ultralaser",
      "category": "tm"
    },
    {
      "id": "leafblade",
      "name": "Lame Feuille",
      "category": "tm"
    },
    {
      "id": "leafstorm",
      "name": "Tempête Verte",
      "category": "tm"
    },
    {
      "id": "lightscreen",
      "name": "Mur Lumière",
      "category": "tm"
    },
    {
      "id": "magicalleaf",
      "name": "Feuille Magik",
      "category": "tm"
    },
    {
      "id": "naturalgift",
      "name": "Don Naturel",
      "category": "tm"
    },
    {
      "id": "naturepower",
      "name": "Force Nature",
      "category": "tm"
    },
    {
      "id": "petalblizzard",
      "name": "Tempête Florale",
      "category": "tm"
    },
    {
      "id": "protect",
      "name": "Abri",
      "category": "tm"
    },
    {
      "id": "raindance",
      "name": "Danse Pluie",
      "category": "tm"
    },
    {
      "id": "rest",
      "name": "Repos",
      "category": "tm"
    },
    {
      "id": "safeguard",
      "name": "Rune Protect",
      "category": "tm"
    },
    {
      "id": "seedbomb",
      "name": "Canon Graine",
      "category": "tm"
    },
    {
      "id": "sleeptalk",
      "name": "Blabla Dodo",
      "category": "tm"
    },
    {
      "id": "sludgebomb",
      "name": "Bombe Beurk",
      "category": "tm"
    },
    {
      "id": "solarbeam",
      "name": "Lance-Soleil",
      "category": "tm"
    },
    {
      "id": "substitute",
      "name": "Clonage",
      "category": "tm"
    },
    {
      "id": "sunnyday",
      "name": "Zénith",
      "category": "tm"
    },
    {
      "id": "swordsdance",
      "name": "Danse Lames",
      "category": "tm"
    },
    {
      "id": "synthesis",
      "name": "Synthèse",
      "category": "tm"
    },
    {
      "id": "takedown",
      "name": "Bélier",
      "category": "tm"
    },
    {
      "id": "terablast",
      "name": "Téra Explosion",
      "category": "tm"
    },
    {
      "id": "trailblaze",
      "name": "Désherbaffe",
      "category": "tm"
    },
    {
      "id": "weatherball",
      "name": "Ball'Météo",
      "category": "tm"
    },
    {
      "id": "worryseed",
      "name": "Soucigraine",
      "category": "tm"
    },
    {
      "id": "afteryou",
      "name": "Après Vous",
      "category": "tutor"
    },
    {
      "id": "dazzlinggleam",
      "name": "Éclat Magique",
      "category": "tutor"
    },
    {
      "id": "earthpower",
      "name": "Telluriforce",
      "category": "tutor"
    },
    {
      "id": "endeavor",
      "name": "Effort",
      "category": "tutor"
    },
    {
      "id": "energyball",
      "name": "Éco-Sphère",
      "category": "tutor"
    },
    {
      "id": "gigadrain",
      "name": "Giga-Sangsue",
      "category": "tutor"
    },
    {
      "id": "gigaimpact",
      "name": "Giga Impact",
      "category": "tutor"
    },
    {
      "id": "grassyglide",
      "name": "Gliss'Herbe",
      "category": "tutor"
    },
    {
      "id": "helpinghand",
      "name": "Coup d'Main",
      "category": "tutor"
    },
    {
      "id": "hyperbeam",
      "name": "Ultralaser",
      "category": "tutor"
    },
    {
      "id": "magicalleaf",
      "name": "Feuille Magik",
      "category": "tutor"
    },
    {
      "id": "rest",
      "name": "Repos",
      "category": "tutor"
    },
    {
      "id": "seedbomb",
      "name": "Canon Graine",
      "category": "tutor"
    },
    {
      "id": "sleeptalk",
      "name": "Blabla Dodo",
      "category": "tutor"
    },
    {
      "id": "synthesis",
      "name": "Synthèse",
      "category": "tutor"
    },
    {
      "id": "worryseed",
      "name": "Soucigraine",
      "category": "tutor"
    },
    {
      "id": "attract",
      "name": "Attraction",
      "category": "legacy"
    },
    {
      "id": "captivate",
      "name": "Séduction",
      "category": "legacy"
    },
    {
      "id": "confide",
      "name": "Confidence",
      "category": "legacy"
    },
    {
      "id": "doubleteam",
      "name": "Reflet",
      "category": "legacy"
    },
    {
      "id": "frustration",
      "name": "Frustration",
      "category": "legacy"
    },
    {
      "id": "hiddenpower",
      "name": "Puissance Cachée",
      "category": "legacy"
    },
    {
      "id": "mimic",
      "name": "Copie",
      "category": "legacy"
    },
    {
      "id": "return",
      "name": "Retour",
      "category": "legacy"
    },
    {
      "id": "round",
      "name": "Chant Canon",
      "category": "legacy"
    },
    {
      "id": "secretpower",
      "name": "Force Cachée",
      "category": "legacy"
    },
    {
      "id": "snore",
      "name": "Ronflement",
      "category": "legacy"
    },
    {
      "id": "swagger",
      "name": "Vantardise",
      "category": "legacy"
    },
    {
      "id": "toxic",
      "name": "Toxik",
      "category": "legacy"
    },
    {
      "id": "uproar",
      "name": "Brouhaha",
      "category": "legacy"
    }
  ],
  "forms": [],
  "evolutions": [],
  "preEvolution": "sunkern",
  "spawns": [
    [
      {
        "presets": [
          "natural"
        ],
        "rarity": "common",
        "weight": 0.5,
        "levels": "13-43",
        "biomeTags": {
          "include": [
            "minecraft:sunflower_plains"
          ]
        },
        "source": "Abes-Hutts-Cobblemon-1.21.1.1.7.3-1.0.2.jar!/data/cobblemon/spawn_pool_world/0192_sunflora.json",
        "spawnId": "sunflora-1",
        "nearbyBlocks": {
          "selectors": [
            "minecraft:sunflower"
          ]
        },
        "sky": {
          "minSkyLight": 8,
          "maxSkyLight": 15
        },
        "spawnType": "grounded",
        "pokemon": "sunflora",
        "type": "pokemon",
        "weightMultiplier": {
          "multiplier": 0.25,
          "condition": {
            "timeRange": "night"
          }
        }
      }
    ],
    [
      {
        "presets": [
          "natural"
        ],
        "rarity": "common",
        "weight": 0.5,
        "levels": "13-43",
        "biomeTags": {
          "include": [
            "#cobblemon:is_overworld"
          ],
          "exclude": [
            "minecraft:sunflower_plains"
          ]
        },
        "source": "Abes-Hutts-Cobblemon-1.21.1.1.7.3-1.0.2.jar!/data/cobblemon/spawn_pool_world/0192_sunflora.json",
        "spawnId": "sunflora-2",
        "nearbyBlocks": {
          "selectors": [
            "minecraft:sunflower"
          ]
        },
        "sky": {
          "minSkyLight": 8,
          "maxSkyLight": 15
        },
        "spawnType": "grounded",
        "pokemon": "sunflora",
        "type": "pokemon",
        "weightMultiplier": {
          "multiplier": 0.25,
          "condition": {
            "timeRange": "night"
          }
        }
      }
    ],
    [
      {
        "presets": [
          "natural"
        ],
        "rarity": "common",
        "weight": 0.3,
        "levels": "13-43",
        "biomeTags": {
          "include": [
            "aether:skyroot_grove",
            "aether:skyroot_meadow"
          ]
        },
        "source": "Abes-Hutts-Cobblemon-1.21.1.1.7.3-1.0.2.jar!/data/cobblemon/spawn_pool_world/0192_sunflora.json",
        "spawnId": "sunflora-3",
        "sky": {
          "minSkyLight": 8,
          "maxSkyLight": 15
        },
        "spawnType": "grounded",
        "pokemon": "sunflora",
        "type": "pokemon"
      }
    ],
    [
      {
        "rarity": "common",
        "weight": 0.5,
        "levels": "13-43",
        "biomeTags": {
          "include": [
            "the_bumblezone:floral_meadow"
          ]
        },
        "source": "Abes-Hutts-Cobblemon-1.21.1.1.7.3-1.0.2.jar!/data/cobblemon/spawn_pool_world/0192_sunflora.json",
        "spawnId": "sunflora-4",
        "spawnType": "grounded",
        "pokemon": "sunflora",
        "excludeStructures": [
          "#the_bumblezone:sempiternal_sanctums"
        ],
        "type": "pokemon"
      }
    ]
  ],
  "implemented": true,
  "images": {
    "normal": [
      "out/sprites/cobblemon/sunflora.png"
    ],
    "shiny": [
      "out/sprites/cobblemon/sunflora_shiny.png"
    ]
  },
  "speciesSources": [
    "Abes-Hutts-Cobblemon-1.21.1.1.7.3-1.0.2.jar!/data/cobblemon/species/generation2/sunflora.json"
  ]
}